[{"index": 20, "state": "com.android.internal.app.ChooserActivity(b4624590) to   mCurrentFocus=Window{b43878b0 u0 StatusBar(b43878b0)", "coverage": "41%  (41/100) to 41%  (41/100)"}, {"index": 21, "state": "  mCurrentFocus=Window{b43878b0 u0 StatusBar(b43878b0) to com.android.internal.app.ChooserActivity(b4624590)", "coverage": "41%  (41/100) to 41%  (41/100)"}, {"index": 32, "state": "com.android.internal.app.ChooserActivity(b4624590) to com.android.settings.applications.InstalledAppDetails(b4146678)", "coverage": "41%  (41/100) to 41%  (41/100)"}, {"index": 36, "state": "com.android.settings.applications.InstalledAppDetails(b4146678) to   mCurrentFocus=Window{b43878b0 u0 StatusBar(b43878b0)", "coverage": "41%  (41/100) to 41%  (41/100)"}]