[{"coverage": "41%  (41/100)", "state": "com.android.launcher2.Launcher(b3e22508)"}, {"coverage": "41%  (41/100)", "state": "com.android.launcher2.Launcher(b3e22508)"}, {"coverage": "41%  (41/100)", "state": "com.android.launcher2.Launcher(b3e22508)"}, {"coverage": "41%  (41/100)", "state": "com.android.launcher2.Launcher(b3e22508)"}, {"coverage": "41%  (41/100)", "state": "com.android.launcher2.Launcher(b3e22508)"}, {"coverage": "41%  (41/100)", "state": "com.android.launcher2.Launcher(b3e22508)"}, {"coverage": "41%  (41/100)", "state": "com.android.launcher2.Launcher(b3e22508)"}, {"coverage": "41%  (41/100)", "state": "com.android.launcher2.Launcher(b3e22508)"}, {"coverage": "41%  (41/100)", "state": "com.android.launcher2.Launcher(b3e22508)"}, {"coverage": "41%  (41/100)", "state": "com.android.launcher2.Launcher(b3e22508)"}, {"coverage": "41%  (41/100)", "state": "org.totschnig.myexpenses.EmmaInstrument.InstrumentedActivity(b41493e8)"}, {"coverage": "41%  (41/100)", "state": "org.totschnig.myexpenses.EmmaInstrument.InstrumentedActivity(b41493e8)"}, {"coverage": "41%  (41/100)", "state": "org.totschnig.myexpenses.EmmaInstrument.InstrumentedActivity(b41493e8)"}, {"coverage": "41%  (41/100)", "state": "org.totschnig.myexpenses.EmmaInstrument.InstrumentedActivity(b41493e8)"}, {"coverage": "41%  (41/100)", "state": "org.totschnig.myexpenses.EmmaInstrument.InstrumentedActivity(b41493e8)"}, {"coverage": "41%  (41/100)", "state": "org.totschnig.myexpenses.EmmaInstrument.InstrumentedActivity(b41493e8)"}, {"coverage": "41%  (41/100)", "state": "org.totschnig.myexpenses.EmmaInstrument.InstrumentedActivity(b41493e8)"}, {"coverage": "41%  (41/100)", "state": "org.totschnig.myexpenses.EmmaInstrument.InstrumentedActivity(b41493e8)"}, {"coverage": "41%  (41/100)", "state": "  mCurrentFocus=Window{b43878b0 u0 StatusBar(b43878b0)"}, {"coverage": "41%  (41/100)", "state": "  mCurrentFocus=Window{b43878b0 u0 StatusBar(b43878b0)"}, {"coverage": "41%  (41/100)", "state": "  mCurrentFocus=Window{b43878b0 u0 StatusBar(b43878b0)"}, {"coverage": "41%  (41/100)", "state": "  mCurrentFocus=Window{b43878b0 u0 StatusBar(b43878b0)"}, {"coverage": "41%  (41/100)", "state": "  mCurrentFocus=Window{b43878b0 u0 StatusBar(b43878b0)"}, {"coverage": "41%  (41/100)", "state": "  mCurrentFocus=Window{b43878b0 u0 StatusBar(b43878b0)"}, {"coverage": "41%  (41/100)", "state": "  mCurrentFocus=Window{b43878b0 u0 StatusBar(b43878b0)"}, {"coverage": "41%  (41/100)", "state": "  mCurrentFocus=Window{b43878b0 u0 StatusBar(b43878b0)"}, {"coverage": "41%  (41/100)", "state": "  mCurrentFocus=Window{b43878b0 u0 StatusBar(b43878b0)"}, {"coverage": "41%  (41/100)", "state": "  mCurrentFocus=Window{b43878b0 u0 StatusBar(b43878b0)"}, {"coverage": "41%  (41/100)", "state": "org.totschnig.myexpenses.EmmaInstrument.InstrumentedActivity(b41493e8)"}, {"coverage": "41%  (41/100)", "state": "org.totschnig.myexpenses.EmmaInstrument.InstrumentedActivity(b41493e8)"}, {"coverage": "41%  (41/100)", "state": "org.totschnig.myexpenses.EmmaInstrument.InstrumentedActivity(b41493e8)"}, {"coverage": "41%  (41/100)", "state": "org.totschnig.myexpenses.EmmaInstrument.InstrumentedActivity(b41493e8)"}, {"coverage": "41%  (41/100)", "state": "org.totschnig.myexpenses.EmmaInstrument.InstrumentedActivity(b41493e8)"}, {"coverage": "41%  (41/100)", "state": "org.totschnig.myexpenses.EmmaInstrument.InstrumentedActivity(b41493e8)"}, {"coverage": "41%  (41/100)", "state": "org.totschnig.myexpenses.EmmaInstrument.InstrumentedActivity(b41493e8)"}, {"coverage": "41%  (41/100)", "state": "org.totschnig.myexpenses.EmmaInstrument.InstrumentedActivity(b41493e8)"}, {"coverage": "41%  (41/100)", "state": "org.totschnig.myexpenses.EmmaInstrument.InstrumentedActivity(b41493e8)"}, {"coverage": "41%  (41/100)", "state": "org.totschnig.myexpenses.EmmaInstrument.InstrumentedActivity(b41493e8)"}, {"coverage": "41%  (41/100)", "state": "org.totschnig.myexpenses.EmmaInstrument.InstrumentedActivity(b41493e8)"}, {"coverage": "41%  (41/100)", "state": "org.totschnig.myexpenses.EmmaInstrument.InstrumentedActivity(b41493e8)"}, {"coverage": "41%  (41/100)", "state": "org.totschnig.myexpenses.EmmaInstrument.InstrumentedActivity(b41493e8)"}, {"coverage": "41%  (41/100)", "state": "org.totschnig.myexpenses.EmmaInstrument.InstrumentedActivity(b41493e8)"}, {"coverage": "41%  (41/100)", "state": "org.totschnig.myexpenses.EmmaInstrument.InstrumentedActivity(b41493e8)"}, {"coverage": "41%  (41/100)", "state": "org.totschnig.myexpenses.EmmaInstrument.InstrumentedActivity(b41493e8)"}, {"coverage": "41%  (41/100)", "state": "org.totschnig.myexpenses.EmmaInstrument.InstrumentedActivity(b41493e8)"}, {"coverage": "41%  (41/100)", "state": "org.totschnig.myexpenses.EmmaInstrument.InstrumentedActivity(b41493e8)"}, {"coverage": "41%  (41/100)", "state": "org.totschnig.myexpenses.EmmaInstrument.InstrumentedActivity(b41493e8)"}, {"coverage": "41%  (41/100)", "state": "org.totschnig.myexpenses.EmmaInstrument.InstrumentedActivity(b41493e8)"}, {"coverage": "41%  (41/100)", "state": "org.totschnig.myexpenses.EmmaInstrument.InstrumentedActivity(b41493e8)"}, {"coverage": "41%  (41/100)", "state": "org.totschnig.myexpenses.EmmaInstrument.InstrumentedActivity(b41493e8)"}, {"coverage": "41%  (41/100)", "state": "org.totschnig.myexpenses.EmmaInstrument.InstrumentedActivity(b41493e8)"}, {"coverage": "41%  (41/100)", "state": "org.totschnig.myexpenses.EmmaInstrument.InstrumentedActivity(b41493e8)"}, {"coverage": "41%  (41/100)", "state": "org.totschnig.myexpenses.EmmaInstrument.InstrumentedActivity(b3f913f8)"}, {"coverage": "41%  (41/100)", "state": "org.totschnig.myexpenses.EmmaInstrument.InstrumentedActivity(b3f913f8)"}, {"coverage": "41%  (41/100)", "state": "org.totschnig.myexpenses.EmmaInstrument.InstrumentedActivity(b3f913f8)"}, {"coverage": "41%  (41/100)", "state": "org.totschnig.myexpenses.EmmaInstrument.InstrumentedActivity(b3f913f8)"}, {"coverage": "41%  (41/100)", "state": "org.totschnig.myexpenses.EmmaInstrument.InstrumentedActivity(b3f913f8)"}, {"coverage": "41%  (41/100)", "state": "org.totschnig.myexpenses.EmmaInstrument.InstrumentedActivity(b3f913f8)"}, {"coverage": "41%  (41/100)", "state": "org.totschnig.myexpenses.EmmaInstrument.InstrumentedActivity(b3f913f8)"}, {"coverage": "41%  (41/100)", "state": "org.totschnig.myexpenses.EmmaInstrument.InstrumentedActivity(b3f913f8)"}, {"coverage": "41%  (41/100)", "state": "org.totschnig.myexpenses.EmmaInstrument.InstrumentedActivity(b3f913f8)"}, {"coverage": "41%  (41/100)", "state": "org.totschnig.myexpenses.EmmaInstrument.InstrumentedActivity(b3f913f8)"}, {"coverage": "41%  (41/100)", "state": "org.totschnig.myexpenses.EmmaInstrument.InstrumentedActivity(b3f913f8)"}, {"coverage": "41%  (41/100)", "state": "org.totschnig.myexpenses.EmmaInstrument.InstrumentedActivity(b3f913f8)"}, {"coverage": "41%  (41/100)", "state": "org.totschnig.myexpenses.EmmaInstrument.InstrumentedActivity(b3f913f8)"}, {"coverage": "41%  (41/100)", "state": "org.totschnig.myexpenses.EmmaInstrument.InstrumentedActivity(b3f913f8)"}, {"coverage": "41%  (41/100)", "state": "org.totschnig.myexpenses.EmmaInstrument.InstrumentedActivity(b3f913f8)"}, {"coverage": "41%  (41/100)", "state": "org.totschnig.myexpenses.EmmaInstrument.InstrumentedActivity(b3f913f8)"}, {"coverage": "41%  (41/100)", "state": "org.totschnig.myexpenses.EmmaInstrument.InstrumentedActivity(b3f913f8)"}, {"coverage": "41%  (41/100)", "state": "org.totschnig.myexpenses.EmmaInstrument.InstrumentedActivity(b3f913f8)"}, {"coverage": "41%  (41/100)", "state": "org.totschnig.myexpenses.EmmaInstrument.InstrumentedActivity(b3f913f8)"}, {"coverage": "41%  (41/100)", "state": "org.totschnig.myexpenses.EmmaInstrument.InstrumentedActivity(b3f913f8)"}, {"coverage": "41%  (41/100)", "state": "org.totschnig.myexpenses.EmmaInstrument.InstrumentedActivity(b3f913f8)"}, {"coverage": "41%  (41/100)", "state": "org.totschnig.myexpenses.EmmaInstrument.InstrumentedActivity(b3f913f8)"}, {"coverage": "41%  (41/100)", "state": "org.totschnig.myexpenses.EmmaInstrument.InstrumentedActivity(b3f913f8)"}, {"coverage": "41%  (41/100)", "state": "org.totschnig.myexpenses.EmmaInstrument.InstrumentedActivity(b3f913f8)"}, {"coverage": "41%  (41/100)", "state": "org.totschnig.myexpenses.EmmaInstrument.InstrumentedActivity(b3f913f8)"}, {"coverage": "41%  (41/100)", "state": "org.totschnig.myexpenses.EmmaInstrument.InstrumentedActivity(b3f913f8)"}, {"coverage": "41%  (41/100)", "state": "org.totschnig.myexpenses.EmmaInstrument.InstrumentedActivity(b3f913f8)"}, {"coverage": "41%  (41/100)", "state": "org.totschnig.myexpenses.EmmaInstrument.InstrumentedActivity(b3f913f8)"}, {"coverage": "41%  (41/100)", "state": "org.totschnig.myexpenses.EmmaInstrument.InstrumentedActivity(b3f913f8)"}, {"coverage": "41%  (41/100)", "state": "org.totschnig.myexpenses.EmmaInstrument.InstrumentedActivity(b3f913f8)"}, {"coverage": "41%  (41/100)", "state": "org.totschnig.myexpenses.EmmaInstrument.InstrumentedActivity(b3f913f8)"}, {"coverage": "41%  (41/100)", "state": "org.totschnig.myexpenses.EmmaInstrument.InstrumentedActivity(b3f913f8)"}, {"coverage": "41%  (41/100)", "state": "org.totschnig.myexpenses.EmmaInstrument.InstrumentedActivity(b3f913f8)"}, {"coverage": "41%  (41/100)", "state": "org.totschnig.myexpenses.EmmaInstrument.InstrumentedActivity(b3f913f8)"}, {"coverage": "41%  (41/100)", "state": "org.totschnig.myexpenses.EmmaInstrument.InstrumentedActivity(b3f913f8)"}, {"coverage": "41%  (41/100)", "state": "org.totschnig.myexpenses.EmmaInstrument.InstrumentedActivity(b3f913f8)"}, {"coverage": "41%  (41/100)", "state": "org.totschnig.myexpenses.EmmaInstrument.InstrumentedActivity(b3f913f8)"}, {"coverage": "41%  (41/100)", "state": "org.totschnig.myexpenses.EmmaInstrument.InstrumentedActivity(b3f913f8)"}, {"coverage": "41%  (41/100)", "state": "org.totschnig.myexpenses.EmmaInstrument.InstrumentedActivity(b3f913f8)"}, {"coverage": "41%  (41/100)", "state": "org.totschnig.myexpenses.EmmaInstrument.InstrumentedActivity(b3f913f8)"}, {"coverage": "41%  (41/100)", "state": "org.totschnig.myexpenses.EmmaInstrument.InstrumentedActivity(b3f913f8)"}, {"coverage": "41%  (41/100)", "state": "org.totschnig.myexpenses.EmmaInstrument.InstrumentedActivity(b3f913f8)"}, {"coverage": "41%  (41/100)", "state": "org.totschnig.myexpenses.EmmaInstrument.InstrumentedActivity(b3f913f8)"}, {"coverage": "41%  (41/100)", "state": "org.totschnig.myexpenses.EmmaInstrument.InstrumentedActivity(b3f913f8)"}, {"coverage": "41%  (41/100)", "state": "org.totschnig.myexpenses.EmmaInstrument.InstrumentedActivity(b3f913f8)"}, {"coverage": "41%  (41/100)", "state": "org.totschnig.myexpenses.EmmaInstrument.InstrumentedActivity(b3f913f8)"}, {"coverage": "41%  (41/100)", "state": "org.totschnig.myexpenses.EmmaInstrument.InstrumentedActivity(b3f913f8)"}, {"coverage": "41%  (41/100)", "state": "org.totschnig.myexpenses.EmmaInstrument.InstrumentedActivity(b3f913f8)"}, {"coverage": "41%  (41/100)", "state": "org.totschnig.myexpenses.EmmaInstrument.InstrumentedActivity(b3d60f18)"}, {"coverage": "41%  (41/100)", "state": "org.totschnig.myexpenses.EmmaInstrument.InstrumentedActivity(b3d60f18)"}, {"coverage": "41%  (41/100)", "state": "org.totschnig.myexpenses.ExpenseEdit(b447eb60)"}, {"coverage": "41%  (41/100)", "state": "org.totschnig.myexpenses.ExpenseEdit(b447eb60)"}, {"coverage": "41%  (41/100)", "state": "org.totschnig.myexpenses.ExpenseEdit(b447eb60)"}, {"coverage": "41%  (41/100)", "state": "org.totschnig.myexpenses.ExpenseEdit(b447eb60)"}, {"coverage": "41%  (41/100)", "state": "org.totschnig.myexpenses.SelectCategory(b3d66c20)"}, {"coverage": "41%  (41/100)", "state": "org.totschnig.myexpenses.SelectCategory(b3d66c20)"}, {"coverage": "41%  (41/100)", "state": "org.totschnig.myexpenses.SelectCategory(b3d66c20)"}, {"coverage": "41%  (41/100)", "state": "org.totschnig.myexpenses.SelectCategory(b3d66c20)"}, {"coverage": "41%  (41/100)", "state": "org.totschnig.myexpenses.SelectCategory(b3d66c20)"}, {"coverage": "41%  (41/100)", "state": "org.totschnig.myexpenses.SelectCategory(b3d66c20)"}, {"coverage": "41%  (41/100)", "state": "org.totschnig.myexpenses.SelectCategory(b3d66c20)"}, {"coverage": "41%  (41/100)", "state": "org.totschnig.myexpenses.SelectCategory(b3d66c20)"}, {"coverage": "41%  (41/100)", "state": "org.totschnig.myexpenses.SelectCategory(b3d66c20)"}, {"coverage": "41%  (41/100)", "state": "org.totschnig.myexpenses.SelectCategory(b3d66c20)"}, {"coverage": "41%  (41/100)", "state": "org.totschnig.myexpenses.SelectCategory(b3d66c20)"}, {"coverage": "41%  (41/100)", "state": "org.totschnig.myexpenses.SelectCategory(b3d66c20)"}, {"coverage": "41%  (41/100)", "state": "org.totschnig.myexpenses.SelectCategory(b3d66c20)"}, {"coverage": "41%  (41/100)", "state": "org.totschnig.myexpenses.SelectCategory(b3d66c20)"}, {"coverage": "41%  (41/100)", "state": "org.totschnig.myexpenses.GrisbiImport(b45fc760)"}, {"coverage": "41%  (41/100)", "state": "org.totschnig.myexpenses.GrisbiImport(b45fc760)"}, {"coverage": "41%  (41/100)", "state": "org.totschnig.myexpenses.GrisbiImport(b45fc760)"}, {"coverage": "41%  (41/100)", "state": "org.totschnig.myexpenses.GrisbiImport(b45fc760)"}, {"coverage": "41%  (41/100)", "state": "org.totschnig.myexpenses.GrisbiImport(b45fc760)"}, {"coverage": "41%  (41/100)", "state": "org.totschnig.myexpenses.GrisbiImport(b45fc760)"}, {"coverage": "41%  (41/100)", "state": "org.totschnig.myexpenses.GrisbiImport(b45fc760)"}, {"coverage": "41%  (41/100)", "state": "org.totschnig.myexpenses.GrisbiImport(b45fc760)"}, {"coverage": "41%  (41/100)", "state": "org.totschnig.myexpenses.GrisbiImport(b45fc760)"}, {"coverage": "41%  (41/100)", "state": "org.totschnig.myexpenses.GrisbiImport(b45fc760)"}, {"coverage": "41%  (41/100)", "state": "org.totschnig.myexpenses.GrisbiImport(b45fc760)"}, {"coverage": "41%  (41/100)", "state": "org.totschnig.myexpenses.GrisbiImport(b45fc760)"}, {"coverage": "41%  (41/100)", "state": "org.totschnig.myexpenses.GrisbiImport(b45fc760)"}, {"coverage": "41%  (41/100)", "state": "org.totschnig.myexpenses.GrisbiImport(b45fc760)"}, {"coverage": "41%  (41/100)", "state": "org.totschnig.myexpenses.GrisbiImport(b45fc760)"}, {"coverage": "41%  (41/100)", "state": "org.totschnig.myexpenses.GrisbiImport(b45fc760)"}, {"coverage": "41%  (41/100)", "state": "org.totschnig.myexpenses.GrisbiImport(b45fc760)"}, {"coverage": "41%  (41/100)", "state": "org.totschnig.myexpenses.GrisbiImport(b45fc760)"}, {"coverage": "41%  (41/100)", "state": "org.totschnig.myexpenses.GrisbiImport(b45fc760)"}, {"coverage": "41%  (41/100)", "state": "org.totschnig.myexpenses.GrisbiImport(b45fc760)"}, {"coverage": "41%  (41/100)", "state": "org.totschnig.myexpenses.GrisbiImport(b45fc760)"}, {"coverage": "41%  (41/100)", "state": "org.totschnig.myexpenses.GrisbiImport(b45fc760)"}, {"coverage": "41%  (41/100)", "state": "org.totschnig.myexpenses.GrisbiImport(b45fc760)"}, {"coverage": "41%  (41/100)", "state": "org.totschnig.myexpenses.GrisbiImport(b45fc760)"}, {"coverage": "41%  (41/100)", "state": "org.totschnig.myexpenses.GrisbiImport(b45fc760)"}, {"coverage": "41%  (41/100)", "state": "org.totschnig.myexpenses.GrisbiImport(b45fc760)"}, {"coverage": "41%  (41/100)", "state": "org.totschnig.myexpenses.GrisbiImport(b45fc760)"}, {"coverage": "41%  (41/100)", "state": "org.totschnig.myexpenses.GrisbiImport(b45fc760)"}, {"coverage": "41%  (41/100)", "state": "org.totschnig.myexpenses.GrisbiImport(b45fc760)"}, {"coverage": "41%  (41/100)", "state": "org.totschnig.myexpenses.GrisbiImport(b45fc760)"}, {"coverage": "41%  (41/100)", "state": "org.totschnig.myexpenses.GrisbiImport(b45fc760)"}, {"coverage": "41%  (41/100)", "state": "org.totschnig.myexpenses.GrisbiImport(b45fc760)"}, {"coverage": "41%  (41/100)", "state": "org.totschnig.myexpenses.GrisbiImport(b45fc760)"}, {"coverage": "41%  (41/100)", "state": "org.totschnig.myexpenses.GrisbiImport(b45fc760)"}, {"coverage": "41%  (41/100)", "state": "org.totschnig.myexpenses.GrisbiImport(b45fc760)"}, {"coverage": "41%  (41/100)", "state": "org.totschnig.myexpenses.GrisbiImport(b45fc760)"}, {"coverage": "41%  (41/100)", "state": "org.totschnig.myexpenses.GrisbiImport(b45fc760)"}, {"coverage": "41%  (41/100)", "state": "org.totschnig.myexpenses.GrisbiImport(b45fc760)"}, {"coverage": "41%  (41/100)", "state": "org.totschnig.myexpenses.GrisbiImport(b45fc760)"}, {"coverage": "41%  (41/100)", "state": "org.totschnig.myexpenses.GrisbiImport(b45fc760)"}, {"coverage": "41%  (41/100)", "state": "org.totschnig.myexpenses.GrisbiImport(b45fc760)"}, {"coverage": "41%  (41/100)", "state": "org.totschnig.myexpenses.GrisbiImport(b45fc760)"}, {"coverage": "41%  (41/100)", "state": "org.totschnig.myexpenses.GrisbiImport(b45fc760)"}, {"coverage": "41%  (41/100)", "state": "org.totschnig.myexpenses.GrisbiImport(b45fc760)"}, {"coverage": "41%  (41/100)", "state": "org.totschnig.myexpenses.GrisbiImport(b45fc760)"}, {"coverage": "41%  (41/100)", "state": "org.totschnig.myexpenses.GrisbiImport(b45fc760)"}, {"coverage": "41%  (41/100)", "state": "org.totschnig.myexpenses.GrisbiImport(b45fc760)"}, {"coverage": "41%  (41/100)", "state": "org.totschnig.myexpenses.GrisbiImport(b45fc760)"}, {"coverage": "41%  (41/100)", "state": "org.totschnig.myexpenses.GrisbiImport(b45fc760)"}, {"coverage": "41%  (41/100)", "state": "org.totschnig.myexpenses.GrisbiImport(b45fc760)"}, {"coverage": "41%  (41/100)", "state": "org.totschnig.myexpenses.GrisbiImport(b45fc760)"}, {"coverage": "41%  (41/100)", "state": "org.totschnig.myexpenses.GrisbiImport(b45fc760)"}, {"coverage": "41%  (41/100)", "state": "org.totschnig.myexpenses.GrisbiImport(b45fc760)"}, {"coverage": "41%  (41/100)", "state": "org.totschnig.myexpenses.GrisbiImport(b45fc760)"}, {"coverage": "41%  (41/100)", "state": "org.totschnig.myexpenses.GrisbiImport(b45fc760)"}, {"coverage": "41%  (41/100)", "state": "org.totschnig.myexpenses.GrisbiImport(b45fc760)"}, {"coverage": "41%  (41/100)", "state": "org.totschnig.myexpenses.GrisbiImport(b45fc760)"}, {"coverage": "41%  (41/100)", "state": "org.totschnig.myexpenses.GrisbiImport(b45fc760)"}, {"coverage": "41%  (41/100)", "state": "org.totschnig.myexpenses.GrisbiImport(b45fc760)"}, {"coverage": "41%  (41/100)", "state": "org.totschnig.myexpenses.GrisbiImport(b45fc760)"}]